{
  "build": {
    "beforeDevCommand": "npm run dev",
    "beforeBuildCommand": "npm run next-build",
    "devPath": "http://localhost:1420",
    "distDir": "../dist",
    "withGlobalTauri": false
  },
  "package": {
    "productName": "SobseedPS Launcher",
    "version": "1.0.1"
  },
  "tauri": {
    "allowlist": {
      "all": false,
      "shell": {
        "all": false,
        "open": true
      }
    },
    "bundle": {
      "active": true,
      "category": "DeveloperTool",
      "copyright": "",
      "deb": {
        "depends": []
      },
      "externalBin": [],
      "icon": [
        "icons/icon.ico",
        "icons/icon.png",
        "icons/32x32.png",
        "icons/128x128.png",
        "icons/128x128@2x.png"
      ],
      "identifier": "SobseedPS",
      "longDescription": "",
      "macOS": {
        "entitlements": null,
        "exceptionDomain": "",
        "frameworks": [],
        "providerShortName": null,
        "signingIdentity": null
      },
      "resources": [],
      "shortDescription": "",
      "targets": "all",
      "windows": {
        "certificateThumbprint": null,
        "digestAlgorithm": "sha256",
        "timestampUrl": ""
      }
    },
    "updater": {
      "active": false
    },
    "security": {
      "csp": null
    },
    "windows": [
      {
        "fullscreen": false,
        "height": 600,
        "resizable": true,
        "title": "SobseedPS Launcher",
        "width": 1120
      }
    ]
  }
}